{
  "id": "card.ogn-195-298",
  "type": "card_record",
  "title": "Rhasa the Sunderer",
  "source_kind": "legacy_local_knowledge_db",
  "source_path": "/Users/eric/.openclaw/quarantine-20260323/old_openclaw_bak_03062026/workspace/databases/knowledge.db",
  "source_date": "2026-03-06T10:11:31.039432Z",
  "trust_level": "derived_verified",
  "status": "reviewed",
  "tags": [
    "card",
    "OGN",
    "Unit",
    "Chaos"
  ],
  "record": {
    "id": "b65f124a-a9bf-412a-889a-a4b6b1f43ecf",
    "name": "Rhasa the Sunderer",
    "riftbound_id": "ogn-195-298",
    "tcgplayer_id": "652985",
    "public_code": "OGN-195/298",
    "collector_number": 195,
    "attributes": {
      "energy": 10,
      "might": 6,
      "power": 1
    },
    "classification": {
      "type": "Unit",
      "supertype": null,
      "rarity": "Rare",
      "domain": [
        "Chaos"
      ]
    },
    "text": {
      "rich": "I cost :rb_energy_1: less for each card in your trash.",
      "plain": "I cost :rb_energy_1: less for each card in your trash."
    },
    "set": {
      "set_id": "OGN",
      "label": "Origins"
    },
    "media": {
      "image_url": "https://cmsassets.rgpub.io/sanity/images/dsfx7636/game_data_live/e34fe8a9ee533dee99f96b4e6677d1edbd6a262d-744x1039.png",
      "artist": "Six More Vodka",
      "accessibility_text": "Rhasa the Sunderer"
    },
    "tags": [
      "Spirit",
      "Shadow Isles"
    ],
    "orientation": "portrait",
    "metadata": {
      "clean_name": "rhasa-the-sunderer",
      "alternate_art": false,
      "signature": false,
      "record_key": "ogn-195-298",
      "source_record_kind": "legacy_local_knowledge_db"
    }
  }
}
