{
  "id": "card.sfd-001-221",
  "type": "card_record",
  "title": "Against the Odds",
  "source_kind": "legacy_local_knowledge_db",
  "source_path": "/Users/eric/.openclaw/quarantine-20260323/old_openclaw_bak_03062026/workspace/databases/knowledge.db",
  "source_date": "2026-03-06T10:11:31.039432Z",
  "trust_level": "derived_verified",
  "status": "reviewed",
  "tags": [
    "card",
    "SFD",
    "Spell",
    "Fury"
  ],
  "record": {
    "id": "8f0af435-d0f5-4a40-ad2b-20a90de30d77",
    "name": "Against the Odds",
    "riftbound_id": "sfd-001-221",
    "tcgplayer_id": "665140",
    "public_code": "SFD-001/221",
    "collector_number": 1,
    "attributes": {
      "energy": 2,
      "might": null,
      "power": null
    },
    "classification": {
      "type": "Spell",
      "supertype": null,
      "rarity": "Common",
      "domain": [
        "Fury"
      ]
    },
    "text": {
      "rich": "[Reaction] (Play any time, even before spells and abilities resolve.)Give a friendly unit at a battlefield +2 :rb_might: this turn for each enemy unit there.",
      "plain": "[Reaction] (Play any time, even before spells and abilities resolve.)Give a friendly unit at a battlefield +2 :rb_might: this turn for each enemy unit there."
    },
    "set": {
      "set_id": "SFD",
      "label": "SFD"
    },
    "media": {
      "image_url": "https://cmsassets.rgpub.io/sanity/images/dsfx7636/game_data_live/4c4ab0c838854ccd5d5399a045835876450287e8-744x1039.png",
      "artist": "Kudos Productions",
      "accessibility_text": "Against the Odds"
    },
    "tags": [],
    "orientation": "portrait",
    "metadata": {
      "clean_name": "against-the-odds",
      "alternate_art": false,
      "signature": false,
      "record_key": "sfd-001-221",
      "source_record_kind": "legacy_local_knowledge_db"
    }
  }
}
