{
  "id": "tournament.skimish-december",
  "type": "tournament_record",
  "title": "Skimish December",
  "source_kind": "legacy_local_knowledge_db",
  "source_path": "/Users/eric/.openclaw/quarantine-20260323/old_openclaw_bak_03062026/workspace/databases/knowledge.db",
  "source_date": "2026-03-06T10:11:31.039432Z",
  "trust_level": "derived_verified",
  "status": "reviewed",
  "tags": [
    "tournament",
    "Constructed",
    "item"
  ],
  "record": {
    "tid": "skimish-december",
    "name": "Skimish December",
    "start_date": 1764954000,
    "format": "Constructed",
    "swiss_rounds": 4,
    "top_cut": 8,
    "participants": 17,
    "city": null,
    "state": null,
    "location": null,
    "country": null
  },
  "rounds": [
    {
      "id": 5963,
      "tid": "skimish-december",
      "round": "Finals",
      "table_num": 1,
      "player1_name": "Tyler B",
      "player1_id": "18YTj0LsKNcr8xCeyfiI",
      "player2_name": "Jordan S",
      "player2_id": "eryxIwkFwHWLozrOxFzH",
      "winner": "Jordan S",
      "status": "Completed"
    },
    {
      "id": 5964,
      "tid": "skimish-december",
      "round": "Top 4",
      "table_num": 1,
      "player1_name": "Kyle H",
      "player1_id": "v3rRvBk55VgBnmMIvnr5",
      "player2_name": "Tyler B",
      "player2_id": "18YTj0LsKNcr8xCeyfiI",
      "winner": "Tyler B",
      "status": "Completed"
    },
    {
      "id": 5966,
      "tid": "skimish-december",
      "round": "Top 8",
      "table_num": 1,
      "player1_name": "Kyle H",
      "player1_id": "v3rRvBk55VgBnmMIvnr5",
      "player2_name": "Adam L",
      "player2_id": "JlZcE2KsJw71lJa2AbTj",
      "winner": "Kyle H",
      "status": "Completed"
    },
    {
      "id": 5965,
      "tid": "skimish-december",
      "round": "Top 4",
      "table_num": 2,
      "player1_name": "Jordan S",
      "player1_id": "eryxIwkFwHWLozrOxFzH",
      "player2_name": "Ian R",
      "player2_id": "46hfErKWQpzgexI2A6zz",
      "winner": "Jordan S",
      "status": "Completed"
    },
    {
      "id": 5967,
      "tid": "skimish-december",
      "round": "Top 8",
      "table_num": 2,
      "player1_name": "Tyler B",
      "player1_id": "18YTj0LsKNcr8xCeyfiI",
      "player2_name": "Kenneth K",
      "player2_id": "BdaUGagAQMp59ZUtpzn7",
      "winner": "Tyler B",
      "status": "Completed"
    },
    {
      "id": 5968,
      "tid": "skimish-december",
      "round": "Top 8",
      "table_num": 3,
      "player1_name": "RG",
      "player1_id": "CNtmjVlCiPnFOkogyMVS",
      "player2_name": "Ian R",
      "player2_id": "46hfErKWQpzgexI2A6zz",
      "winner": "Ian R",
      "status": "Completed"
    },
    {
      "id": 5969,
      "tid": "skimish-december",
      "round": "Top 8",
      "table_num": 4,
      "player1_name": "Jordan S",
      "player1_id": "eryxIwkFwHWLozrOxFzH",
      "player2_name": "Darrell M",
      "player2_id": "nvHTYlAvuTGWUelK515j",
      "winner": "Jordan S",
      "status": "Completed"
    },
    {
      "id": 5931,
      "tid": "skimish-december",
      "round": "1",
      "table_num": 1,
      "player1_name": "Lee W",
      "player1_id": "EhaZIUkKYiu2Ik3KDQnP",
      "player2_name": "Tyler B",
      "player2_id": "18YTj0LsKNcr8xCeyfiI",
      "winner": "Tyler B",
      "status": "Completed"
    },
    {
      "id": 5932,
      "tid": "skimish-december",
      "round": "1",
      "table_num": 2,
      "player1_name": "Kerry Speegler",
      "player1_id": "Fy8L1v4Be88qeGz9Z3Pb",
      "player2_name": "Andrew S",
      "player2_id": "U7Rd1YCULoZN12D7hflG",
      "winner": "Andrew S",
      "status": "Completed"
    },
    {
      "id": 5933,
      "tid": "skimish-december",
      "round": "1",
      "table_num": 3,
      "player1_name": "Kenneth K",
      "player1_id": "BdaUGagAQMp59ZUtpzn7",
      "player2_name": "Jordan S",
      "player2_id": "eryxIwkFwHWLozrOxFzH",
      "winner": "Jordan S",
      "status": "Completed"
    },
    {
      "id": 5934,
      "tid": "skimish-december",
      "round": "1",
      "table_num": 4,
      "player1_name": "Vick Rushlander",
      "player1_id": "IM2uEacRXvaXlngTZ9Dz",
      "player2_name": "Adam L",
      "player2_id": "JlZcE2KsJw71lJa2AbTj",
      "winner": "Adam L",
      "status": "Completed"
    },
    {
      "id": 5935,
      "tid": "skimish-december",
      "round": "1",
      "table_num": 5,
      "player1_name": "Ian R",
      "player1_id": "46hfErKWQpzgexI2A6zz",
      "player2_name": "James Cabbery",
      "player2_id": "3Zhh82u3c49A9OvHfjPG",
      "winner": "Ian R",
      "status": "Completed"
    },
    {
      "id": 5936,
      "tid": "skimish-december",
      "round": "1",
      "table_num": 6,
      "player1_name": "Kyle H",
      "player1_id": "v3rRvBk55VgBnmMIvnr5",
      "player2_name": "Harold Morton",
      "player2_id": "VvdPrgaM4lQs8hTYUNMV",
      "winner": "Kyle H",
      "status": "Completed"
    },
    {
      "id": 5937,
      "tid": "skimish-december",
      "round": "1",
      "table_num": 7,
      "player1_name": "Cody Wagner",
      "player1_id": "Y8c7etp7I0PTHTr8UWCy",
      "player2_name": "RG",
      "player2_id": "CNtmjVlCiPnFOkogyMVS",
      "winner": "RG",
      "status": "Completed"
    },
    {
      "id": 5938,
      "tid": "skimish-december",
      "round": "1",
      "table_num": 8,
      "player1_name": "Darrell M",
      "player1_id": "nvHTYlAvuTGWUelK515j",
      "player2_name": "Ben McGavin",
      "player2_id": "wnVjTo56r4zYGdE70PmG",
      "winner": "Darrell M",
      "status": "Completed"
    },
    {
      "id": 5939,
      "tid": "skimish-december",
      "round": "2",
      "table_num": 1,
      "player1_name": "Andrew S",
      "player1_id": "U7Rd1YCULoZN12D7hflG",
      "player2_name": "RG",
      "player2_id": "CNtmjVlCiPnFOkogyMVS",
      "winner": "RG",
      "status": "Completed"
    },
    {
      "id": 5940,
      "tid": "skimish-december",
      "round": "2",
      "table_num": 2,
      "player1_name": "Ian R",
      "player1_id": "46hfErKWQpzgexI2A6zz",
      "player2_name": "Adam L",
      "player2_id": "JlZcE2KsJw71lJa2AbTj",
      "winner": "Ian R",
      "status": "Completed"
    },
    {
      "id": 5941,
      "tid": "skimish-december",
      "round": "2",
      "table_num": 3,
      "player1_name": "Jason Lewiki",
      "player1_id": "OWPXtdMn8KjOMG8rAyge",
      "player2_name": "Kyle H",
      "player2_id": "v3rRvBk55VgBnmMIvnr5",
      "winner": "Kyle H",
      "status": "Completed"
    },
    {
      "id": 5942,
      "tid": "skimish-december",
      "round": "2",
      "table_num": 4,
      "player1_name": "Tyler B",
      "player1_id": "18YTj0LsKNcr8xCeyfiI",
      "player2_name": "Darrell M",
      "player2_id": "nvHTYlAvuTGWUelK515j",
      "winner": "Tyler B",
      "status": "Completed"
    },
    {
      "id": 5943,
      "tid": "skimish-december",
      "round": "2",
      "table_num": 5,
      "player1_name": "Jordan S",
      "player1_id": "eryxIwkFwHWLozrOxFzH",
      "player2_name": "James Cabbery",
      "player2_id": "3Zhh82u3c49A9OvHfjPG",
      "winner": "Jordan S",
      "status": "Completed"
    },
    {
      "id": 5944,
      "tid": "skimish-december",
      "round": "2",
      "table_num": 6,
      "player1_name": "Cody Wagner",
      "player1_id": "Y8c7etp7I0PTHTr8UWCy",
      "player2_name": "Vick Rushlander",
      "player2_id": "IM2uEacRXvaXlngTZ9Dz",
      "winner": "Vick Rushlander",
      "status": "Completed"
    },
    {
      "id": 5945,
      "tid": "skimish-december",
      "round": "2",
      "table_num": 7,
      "player1_name": "Lee W",
      "player1_id": "EhaZIUkKYiu2Ik3KDQnP",
      "player2_name": "Harold Morton",
      "player2_id": "VvdPrgaM4lQs8hTYUNMV",
      "winner": "Harold Morton",
      "status": "Completed"
    },
    {
      "id": 5946,
      "tid": "skimish-december",
      "round": "2",
      "table_num": 8,
      "player1_name": "Kerry Speegler",
      "player1_id": "Fy8L1v4Be88qeGz9Z3Pb",
      "player2_name": "Ben McGavin",
      "player2_id": "wnVjTo56r4zYGdE70PmG",
      "winner": "Ben McGavin",
      "status": "Completed"
    },
    {
      "id": 5947,
      "tid": "skimish-december",
      "round": "3",
      "table_num": 1,
      "player1_name": "Tyler B",
      "player1_id": "18YTj0LsKNcr8xCeyfiI",
      "player2_name": "Kyle H",
      "player2_id": "v3rRvBk55VgBnmMIvnr5",
      "winner": "Kyle H",
      "status": "Completed"
    },
    {
      "id": 5948,
      "tid": "skimish-december",
      "round": "3",
      "table_num": 2,
      "player1_name": "RG",
      "player1_id": "CNtmjVlCiPnFOkogyMVS",
      "player2_name": "Ian R",
      "player2_id": "46hfErKWQpzgexI2A6zz",
      "winner": "Draw",
      "status": "Completed"
    },
    {
      "id": 5949,
      "tid": "skimish-december",
      "round": "3",
      "table_num": 3,
      "player1_name": "Jordan S",
      "player1_id": "eryxIwkFwHWLozrOxFzH",
      "player2_name": "Vick Rushlander",
      "player2_id": "IM2uEacRXvaXlngTZ9Dz",
      "winner": "Jordan S",
      "status": "Completed"
    },
    {
      "id": 5950,
      "tid": "skimish-december",
      "round": "3",
      "table_num": 4,
      "player1_name": "Andrew S",
      "player1_id": "U7Rd1YCULoZN12D7hflG",
      "player2_name": "Adam L",
      "player2_id": "JlZcE2KsJw71lJa2AbTj",
      "winner": "Adam L",
      "status": "Completed"
    },
    {
      "id": 5951,
      "tid": "skimish-december",
      "round": "3",
      "table_num": 5,
      "player1_name": "Harold Morton",
      "player1_id": "VvdPrgaM4lQs8hTYUNMV",
      "player2_name": "Darrell M",
      "player2_id": "nvHTYlAvuTGWUelK515j",
      "winner": "Darrell M",
      "status": "Completed"
    },
    {
      "id": 5952,
      "tid": "skimish-december",
      "round": "3",
      "table_num": 6,
      "player1_name": "Kenneth K",
      "player1_id": "BdaUGagAQMp59ZUtpzn7",
      "player2_name": "Jason Lewiki",
      "player2_id": "OWPXtdMn8KjOMG8rAyge",
      "winner": "Kenneth K",
      "status": "Completed"
    },
    {
      "id": 5953,
      "tid": "skimish-december",
      "round": "3",
      "table_num": 7,
      "player1_name": "Ben McGavin",
      "player1_id": "wnVjTo56r4zYGdE70PmG",
      "player2_name": "James Cabbery",
      "player2_id": "3Zhh82u3c49A9OvHfjPG",
      "winner": "James Cabbery",
      "status": "Completed"
    },
    {
      "id": 5954,
      "tid": "skimish-december",
      "round": "3",
      "table_num": 8,
      "player1_name": "Lee W",
      "player1_id": "EhaZIUkKYiu2Ik3KDQnP",
      "player2_name": "Cody Wagner",
      "player2_id": "Y8c7etp7I0PTHTr8UWCy",
      "winner": "Lee W",
      "status": "Completed"
    },
    {
      "id": 5955,
      "tid": "skimish-december",
      "round": "4",
      "table_num": 1,
      "player1_name": "Jordan S",
      "player1_id": "eryxIwkFwHWLozrOxFzH",
      "player2_name": "Kyle H",
      "player2_id": "v3rRvBk55VgBnmMIvnr5",
      "winner": "Draw",
      "status": "Completed"
    },
    {
      "id": 5956,
      "tid": "skimish-december",
      "round": "4",
      "table_num": 2,
      "player1_name": "Ian R",
      "player1_id": "46hfErKWQpzgexI2A6zz",
      "player2_name": "Tyler B",
      "player2_id": "18YTj0LsKNcr8xCeyfiI",
      "winner": "Tyler B",
      "status": "Completed"
    },
    {
      "id": 5957,
      "tid": "skimish-december",
      "round": "4",
      "table_num": 3,
      "player1_name": "RG",
      "player1_id": "CNtmjVlCiPnFOkogyMVS",
      "player2_name": "Adam L",
      "player2_id": "JlZcE2KsJw71lJa2AbTj",
      "winner": "RG",
      "status": "Completed"
    },
    {
      "id": 5958,
      "tid": "skimish-december",
      "round": "4",
      "table_num": 4,
      "player1_name": "Kenneth K",
      "player1_id": "BdaUGagAQMp59ZUtpzn7",
      "player2_name": "Darrell M",
      "player2_id": "nvHTYlAvuTGWUelK515j",
      "winner": "Kenneth K",
      "status": "Completed"
    },
    {
      "id": 5959,
      "tid": "skimish-december",
      "round": "4",
      "table_num": 5,
      "player1_name": "Jason Lewiki",
      "player1_id": "OWPXtdMn8KjOMG8rAyge",
      "player2_name": "Lee W",
      "player2_id": "EhaZIUkKYiu2Ik3KDQnP",
      "winner": "Lee W",
      "status": "Completed"
    },
    {
      "id": 5960,
      "tid": "skimish-december",
      "round": "4",
      "table_num": 6,
      "player1_name": "Harold Morton",
      "player1_id": "VvdPrgaM4lQs8hTYUNMV",
      "player2_name": "Kerry Speegler",
      "player2_id": "Fy8L1v4Be88qeGz9Z3Pb",
      "winner": "Kerry Speegler",
      "status": "Completed"
    },
    {
      "id": 5961,
      "tid": "skimish-december",
      "round": "4",
      "table_num": 7,
      "player1_name": "Vick Rushlander",
      "player1_id": "IM2uEacRXvaXlngTZ9Dz",
      "player2_name": "Ben McGavin",
      "player2_id": "wnVjTo56r4zYGdE70PmG",
      "winner": "Ben McGavin",
      "status": "Completed"
    },
    {
      "id": 5962,
      "tid": "skimish-december",
      "round": "4",
      "table_num": 8,
      "player1_name": "James Cabbery",
      "player1_id": "3Zhh82u3c49A9OvHfjPG",
      "player2_name": "Andrew S",
      "player2_id": "U7Rd1YCULoZN12D7hflG",
      "winner": "Andrew S",
      "status": "Completed"
    }
  ],
  "standings": [
    {
      "id": 2566,
      "tid": "skimish-december",
      "player_name": "Jordan S",
      "player_id": "eryxIwkFwHWLozrOxFzH",
      "placement": 1,
      "wins": 6,
      "wins_swiss": 3,
      "wins_bracket": 3,
      "losses": 0,
      "losses_swiss": 0,
      "losses_bracket": 0,
      "draws": 1,
      "decklist": null,
      "deck_obj": null,
      "deck_obj_parsed": null,
      "decklist_lines": []
    },
    {
      "id": 2567,
      "tid": "skimish-december",
      "player_name": "Tyler B",
      "player_id": "18YTj0LsKNcr8xCeyfiI",
      "placement": 2,
      "wins": 5,
      "wins_swiss": 3,
      "wins_bracket": 2,
      "losses": 2,
      "losses_swiss": 1,
      "losses_bracket": 1,
      "draws": 0,
      "decklist": null,
      "deck_obj": null,
      "deck_obj_parsed": null,
      "decklist_lines": []
    },
    {
      "id": 2568,
      "tid": "skimish-december",
      "player_name": "Kyle H",
      "player_id": "v3rRvBk55VgBnmMIvnr5",
      "placement": 3,
      "wins": 4,
      "wins_swiss": 3,
      "wins_bracket": 1,
      "losses": 1,
      "losses_swiss": 0,
      "losses_bracket": 1,
      "draws": 1,
      "decklist": null,
      "deck_obj": null,
      "deck_obj_parsed": null,
      "decklist_lines": []
    },
    {
      "id": 2569,
      "tid": "skimish-december",
      "player_name": "Ian R",
      "player_id": "46hfErKWQpzgexI2A6zz",
      "placement": 4,
      "wins": 3,
      "wins_swiss": 2,
      "wins_bracket": 1,
      "losses": 2,
      "losses_swiss": 1,
      "losses_bracket": 1,
      "draws": 1,
      "decklist": null,
      "deck_obj": null,
      "deck_obj_parsed": null,
      "decklist_lines": []
    },
    {
      "id": 2570,
      "tid": "skimish-december",
      "player_name": "RG",
      "player_id": "CNtmjVlCiPnFOkogyMVS",
      "placement": 5,
      "wins": 3,
      "wins_swiss": 3,
      "wins_bracket": 0,
      "losses": 1,
      "losses_swiss": 0,
      "losses_bracket": 1,
      "draws": 1,
      "decklist": null,
      "deck_obj": null,
      "deck_obj_parsed": null,
      "decklist_lines": []
    },
    {
      "id": 2571,
      "tid": "skimish-december",
      "player_name": "Kenneth K",
      "player_id": "BdaUGagAQMp59ZUtpzn7",
      "placement": 6,
      "wins": 2,
      "wins_swiss": 2,
      "wins_bracket": 0,
      "losses": 2,
      "losses_swiss": 1,
      "losses_bracket": 1,
      "draws": 0,
      "decklist": null,
      "deck_obj": null,
      "deck_obj_parsed": null,
      "decklist_lines": []
    },
    {
      "id": 2572,
      "tid": "skimish-december",
      "player_name": "Darrell M",
      "player_id": "nvHTYlAvuTGWUelK515j",
      "placement": 7,
      "wins": 2,
      "wins_swiss": 2,
      "wins_bracket": 0,
      "losses": 3,
      "losses_swiss": 2,
      "losses_bracket": 1,
      "draws": 0,
      "decklist": null,
      "deck_obj": null,
      "deck_obj_parsed": null,
      "decklist_lines": []
    },
    {
      "id": 2573,
      "tid": "skimish-december",
      "player_name": "Adam L",
      "player_id": "JlZcE2KsJw71lJa2AbTj",
      "placement": 8,
      "wins": 2,
      "wins_swiss": 2,
      "wins_bracket": 0,
      "losses": 3,
      "losses_swiss": 2,
      "losses_bracket": 1,
      "draws": 0,
      "decklist": null,
      "deck_obj": null,
      "deck_obj_parsed": null,
      "decklist_lines": []
    },
    {
      "id": 2574,
      "tid": "skimish-december",
      "player_name": "Andrew S",
      "player_id": "U7Rd1YCULoZN12D7hflG",
      "placement": 9,
      "wins": 2,
      "wins_swiss": 2,
      "wins_bracket": 0,
      "losses": 2,
      "losses_swiss": 2,
      "losses_bracket": 0,
      "draws": 0,
      "decklist": null,
      "deck_obj": null,
      "deck_obj_parsed": null,
      "decklist_lines": []
    },
    {
      "id": 2575,
      "tid": "skimish-december",
      "player_name": "Kerry Speegler",
      "player_id": "Fy8L1v4Be88qeGz9Z3Pb",
      "placement": 10,
      "wins": 1,
      "wins_swiss": 1,
      "wins_bracket": 0,
      "losses": 2,
      "losses_swiss": 2,
      "losses_bracket": 0,
      "draws": 0,
      "decklist": null,
      "deck_obj": null,
      "deck_obj_parsed": null,
      "decklist_lines": []
    },
    {
      "id": 2576,
      "tid": "skimish-december",
      "player_name": "Lee W",
      "player_id": "EhaZIUkKYiu2Ik3KDQnP",
      "placement": 11,
      "wins": 2,
      "wins_swiss": 2,
      "wins_bracket": 0,
      "losses": 2,
      "losses_swiss": 2,
      "losses_bracket": 0,
      "draws": 0,
      "decklist": null,
      "deck_obj": null,
      "deck_obj_parsed": null,
      "decklist_lines": []
    },
    {
      "id": 2577,
      "tid": "skimish-december",
      "player_name": "Ben McGavin",
      "player_id": "wnVjTo56r4zYGdE70PmG",
      "placement": 12,
      "wins": 2,
      "wins_swiss": 2,
      "wins_bracket": 0,
      "losses": 2,
      "losses_swiss": 2,
      "losses_bracket": 0,
      "draws": 0,
      "decklist": null,
      "deck_obj": null,
      "deck_obj_parsed": null,
      "decklist_lines": []
    },
    {
      "id": 2578,
      "tid": "skimish-december",
      "player_name": "Jason Lewiki",
      "player_id": "OWPXtdMn8KjOMG8rAyge",
      "placement": 13,
      "wins": 0,
      "wins_swiss": 0,
      "wins_bracket": 0,
      "losses": 3,
      "losses_swiss": 3,
      "losses_bracket": 0,
      "draws": 0,
      "decklist": null,
      "deck_obj": null,
      "deck_obj_parsed": null,
      "decklist_lines": []
    },
    {
      "id": 2579,
      "tid": "skimish-december",
      "player_name": "James Cabbery",
      "player_id": "3Zhh82u3c49A9OvHfjPG",
      "placement": 14,
      "wins": 1,
      "wins_swiss": 1,
      "wins_bracket": 0,
      "losses": 3,
      "losses_swiss": 3,
      "losses_bracket": 0,
      "draws": 0,
      "decklist": null,
      "deck_obj": null,
      "deck_obj_parsed": null,
      "decklist_lines": []
    },
    {
      "id": 2580,
      "tid": "skimish-december",
      "player_name": "Harold Morton",
      "player_id": "VvdPrgaM4lQs8hTYUNMV",
      "placement": 15,
      "wins": 1,
      "wins_swiss": 1,
      "wins_bracket": 0,
      "losses": 3,
      "losses_swiss": 3,
      "losses_bracket": 0,
      "draws": 0,
      "decklist": null,
      "deck_obj": null,
      "deck_obj_parsed": null,
      "decklist_lines": []
    },
    {
      "id": 2581,
      "tid": "skimish-december",
      "player_name": "Cody Wagner",
      "player_id": "Y8c7etp7I0PTHTr8UWCy",
      "placement": 16,
      "wins": 0,
      "wins_swiss": 0,
      "wins_bracket": 0,
      "losses": 3,
      "losses_swiss": 3,
      "losses_bracket": 0,
      "draws": 0,
      "decklist": null,
      "deck_obj": null,
      "deck_obj_parsed": null,
      "decklist_lines": []
    },
    {
      "id": 2582,
      "tid": "skimish-december",
      "player_name": "Vick Rushlander",
      "player_id": "IM2uEacRXvaXlngTZ9Dz",
      "placement": 17,
      "wins": 1,
      "wins_swiss": 1,
      "wins_bracket": 0,
      "losses": 3,
      "losses_swiss": 3,
      "losses_bracket": 0,
      "draws": 0,
      "decklist": null,
      "deck_obj": null,
      "deck_obj_parsed": null,
      "decklist_lines": []
    }
  ]
}
