{
  "id": "ruling.rumble-hotheaded--ruling--28",
  "type": "ruling_record",
  "title": "Rumble, Hotheaded (ruling)",
  "source_kind": "legacy_local_knowledge_db",
  "source_path": "/Users/eric/.openclaw/quarantine-20260323/old_openclaw_bak_03062026/workspace/databases/knowledge.db",
  "source_date": "2026-03-06T10:11:31.039432Z",
  "trust_level": "derived_verified",
  "status": "reviewed",
  "tags": [
    "ruling",
    "ruling",
    "rumble-hotheaded"
  ],
  "record": {
    "id": 28,
    "card_name": "Rumble, Hotheaded",
    "ruling_type": "ruling",
    "old_text": null,
    "new_text": null,
    "explanation": "Can choose a Mech token to recycle. Tokens inherit recycle destination of their type, then vanish. Still counts as 'the unit you recycled'.",
    "source_doc": "Spiritforged FAQ",
    "source_url": "https://riftbound.leagueoflegends.com/en-us/news/rules-and-releases/riftbound-spiritforged-faq/",
    "effective_date": "2026-01-14"
  }
}
