{
  "id": "price_history.ogs--petty-officer",
  "type": "price_record",
  "title": "Petty Officer (OGS)",
  "source_kind": "legacy_local_knowledge_db",
  "source_path": "/Users/eric/.openclaw/quarantine-20260323/old_openclaw_bak_03062026/workspace/databases/knowledge.db",
  "source_date": "2026-03-06T10:11:31.039432Z",
  "trust_level": "derived_verified",
  "status": "reviewed",
  "tags": [
    "price-history",
    "OGS",
    "petty-officer"
  ],
  "record": {
    "card_name": "Petty Officer",
    "set_id": "OGS",
    "latest": {
      "card_name": "Petty Officer",
      "set_id": "OGS",
      "tcgplayer_id": "653009",
      "market_price": 0.04,
      "low_price": null,
      "mid_price": null,
      "high_price": null,
      "date": "2026-02-27"
    },
    "history": [
      {
        "card_name": "Petty Officer",
        "set_id": "OGS",
        "tcgplayer_id": "653009",
        "market_price": 0.04,
        "low_price": null,
        "mid_price": null,
        "high_price": null,
        "date": "2026-02-27"
      }
    ]
  }
}
