{
  "id": "price_history.sfd--honest-broker",
  "type": "price_record",
  "title": "Honest Broker (SFD)",
  "source_kind": "legacy_local_knowledge_db",
  "source_path": "/Users/eric/.openclaw/quarantine-20260323/old_openclaw_bak_03062026/workspace/databases/knowledge.db",
  "source_date": "2026-03-06T10:11:31.039432Z",
  "trust_level": "derived_verified",
  "status": "reviewed",
  "tags": [
    "price-history",
    "SFD",
    "honest-broker"
  ],
  "record": {
    "card_name": "Honest Broker",
    "set_id": "SFD",
    "latest": {
      "card_name": "Honest Broker",
      "set_id": "SFD",
      "tcgplayer_id": "664946",
      "market_price": 0.12,
      "low_price": null,
      "mid_price": null,
      "high_price": null,
      "date": "2026-03-01"
    },
    "history": [
      {
        "card_name": "Honest Broker",
        "set_id": "SFD",
        "tcgplayer_id": "664946",
        "market_price": 0.13,
        "low_price": null,
        "mid_price": null,
        "high_price": null,
        "date": "2026-02-27"
      },
      {
        "card_name": "Honest Broker",
        "set_id": "SFD",
        "tcgplayer_id": "664946",
        "market_price": 0.12,
        "low_price": null,
        "mid_price": null,
        "high_price": null,
        "date": "2026-03-01"
      }
    ]
  }
}
